project_func/.gitignore
project_func/__init__.py
project_func/scripts/__init__.py
project_func/scripts/cli.py
project_func/scripts/database.py
project_func/scripts/engine.py
project_func/scripts/main_base.py
project_kuzmenka_24_565-0.1.0.dist-info/METADATA
project_kuzmenka_24_565-0.1.0.dist-info/WHEEL
project_kuzmenka_24_565-0.1.0.dist-info/entry_points.txt
project_kuzmenka_24_565-0.1.0.dist-info/RECORD
