Metadata-Version: 2.1
Name: project_kuzmenka_24-565
Version: 0.1.0
Summary: 
Requires-Python: >=3.12,<4.0
Classifier: Programming Language :: Python :: 3
Classifier: Programming Language :: Python :: 3.12
Requires-Dist: prompt (>=0.4.1,<0.5.0)
